plone.classicui-1.0.1-py3.13-nspkg.pth
plone/classicui/__init__.py
plone/classicui/configure.zcml
plone/classicui/dependencies.zcml
plone/classicui/distributions.zcml
plone/classicui/testing.py
plone/classicui/distributions/classic/image.png
plone/classicui/distributions/classic/profiles.json
plone/classicui/distributions/classic/schema.json
plone/classicui/distributions/classic/content/portlets.json
plone/classicui/distributions/classic/content/principals.json
plone/classicui/distributions/classic/content/redirects.json
plone/classicui/distributions/classic/content/relations.json
plone/classicui/distributions/classic/content/content/__metadata__.json
plone/classicui/distributions/classic/content/content/4053ffb6901342ac991afb54da15ab77/data.json
plone/classicui/distributions/classic/content/content/54163be595184b4eb0a0b82a58b8def8/data.json
plone/classicui/distributions/classic/content/content/61f6d382910945ea95f2e78a14ebb170/data.json
plone/classicui/distributions/classic/content/content/ab584c1a6fae465da2283a0962f80114/data.json
plone/classicui/distributions/classic/content/content/ee556c50736a4650839e2ada6dd65454/data.json
plone/classicui/distributions/classic/content/content/plone_site_root/data.json
plone_classicui-1.0.1.dist-info/METADATA
plone_classicui-1.0.1.dist-info/WHEEL
plone_classicui-1.0.1.dist-info/entry_points.txt
plone_classicui-1.0.1.dist-info/namespace_packages.txt
plone_classicui-1.0.1.dist-info/top_level.txt
plone_classicui-1.0.1.dist-info/RECORD
